{
  "summary": {
    "total": 21,
    "passed": 21,
    "failed": 0,
    "skipped": 0
  },
  "results": [
    {
      "testName": "adventure-log - Default",
      "status": "passed",
      "duration": 575.8999999999942
    },
    {
      "testName": "daily-achievement - Achieved",
      "status": "passed",
      "duration": 382.3999999999942
    },
    {
      "testName": "daily-achievement - Default",
      "status": "passed",
      "duration": 382.70000000001164
    },
    {
      "testName": "daily-achievement - NoData",
      "status": "passed",
      "duration": 382.5
    },
    {
      "testName": "daily-achievement - Today",
      "status": "passed",
      "duration": 383.3999999999942
    },
    {
      "testName": "date-navigation-date-navigation - Default",
      "status": "passed",
      "duration": 384.1000000000058
    },
    {
      "testName": "date-navigation-date-navigation - DifferentDate",
      "status": "passed",
      "duration": 385.5999999999767
    },
    {
      "testName": "entity-icon - AllTypes",
      "status": "passed",
      "duration": 402.8999999999942
    },
    {
      "testName": "entity-icon - Default",
      "status": "passed",
      "duration": 377.8999999999942
    },
    {
      "testName": "entity-icon - WithAnimation",
      "status": "passed",
      "duration": 384.6000000000058
    },
    {
      "testName": "entity-link - Default",
      "status": "passed",
      "duration": 379.8999999999942
    },
    {
      "testName": "entity-stats - Default",
      "status": "passed",
      "duration": 393.0999999999767
    },
    {
      "testName": "entity-stats - HighActivity",
      "status": "passed",
      "duration": 382.1000000000058
    },
    {
      "testName": "entity-stats - NeverExecuted",
      "status": "passed",
      "duration": 383.6000000000058
    },
    {
      "testName": "entity-stats - NewEntity",
      "status": "passed",
      "duration": 384.1000000000058
    },
    {
      "testName": "example - Default",
      "status": "passed",
      "duration": 371.29999999998836
    },
    {
      "testName": "example - WithIcon",
      "status": "passed",
      "duration": 367.79999999998836
    },
    {
      "testName": "header - Default",
      "status": "passed",
      "duration": 383.3999999999942
    },
    {
      "testName": "mission - Default",
      "status": "passed",
      "duration": 388
    },
    {
      "testName": "mission - Incomplete",
      "status": "passed",
      "duration": 382.20000000001164
    },
    {
      "testName": "navigation - Default",
      "status": "passed",
      "duration": 382.1000000000058
    }
  ],
  "generatedAt": "2026-01-19T19:39:59.874Z"
}