{
  "summary": {
    "total": 25,
    "passed": 25,
    "failed": 0,
    "skipped": 0
  },
  "results": [
    {
      "testName": "adventure-log - Default",
      "status": "passed",
      "duration": 565.8999999999942
    },
    {
      "testName": "daily-achievement - Achieved",
      "status": "passed",
      "duration": 383.1000000000058
    },
    {
      "testName": "daily-achievement - Default",
      "status": "passed",
      "duration": 366.69999999998254
    },
    {
      "testName": "daily-achievement - NoData",
      "status": "passed",
      "duration": 366
    },
    {
      "testName": "daily-achievement - Today",
      "status": "passed",
      "duration": 366.6000000000058
    },
    {
      "testName": "date-navigation-date-navigation - Default",
      "status": "passed",
      "duration": 368.1000000000058
    },
    {
      "testName": "date-navigation-date-navigation - DifferentDate",
      "status": "passed",
      "duration": 365.30000000001746
    },
    {
      "testName": "entity-icon - AllTypes",
      "status": "passed",
      "duration": 386.70000000001164
    },
    {
      "testName": "entity-icon - Default",
      "status": "passed",
      "duration": 377.6000000000058
    },
    {
      "testName": "entity-icon - WithAnimation",
      "status": "passed",
      "duration": 369.30000000001746
    },
    {
      "testName": "entity-link - Default",
      "status": "passed",
      "duration": 383.5
    },
    {
      "testName": "entity-link - Disabled",
      "status": "passed",
      "duration": 366.3999999999942
    },
    {
      "testName": "entity-link - LongDescription",
      "status": "passed",
      "duration": 370.1000000000058
    },
    {
      "testName": "entity-link - WithQuickAction",
      "status": "passed",
      "duration": 380.29999999998836
    },
    {
      "testName": "entity-link - WithQuickActionLongDescription",
      "status": "passed",
      "duration": 368.20000000001164
    },
    {
      "testName": "entity-stats - Default",
      "status": "passed",
      "duration": 386.5
    },
    {
      "testName": "entity-stats - HighActivity",
      "status": "passed",
      "duration": 382.69999999998254
    },
    {
      "testName": "entity-stats - NeverExecuted",
      "status": "passed",
      "duration": 383.20000000001164
    },
    {
      "testName": "entity-stats - NewEntity",
      "status": "passed",
      "duration": 384
    },
    {
      "testName": "example - Default",
      "status": "passed",
      "duration": 356.9000000000233
    },
    {
      "testName": "example - WithIcon",
      "status": "passed",
      "duration": 366.80000000001746
    },
    {
      "testName": "header - Default",
      "status": "passed",
      "duration": 367.0999999999767
    },
    {
      "testName": "mission - Default",
      "status": "passed",
      "duration": 371.20000000001164
    },
    {
      "testName": "mission - Incomplete",
      "status": "passed",
      "duration": 382.19999999998254
    },
    {
      "testName": "navigation - Default",
      "status": "passed",
      "duration": 365.3999999999942
    }
  ],
  "generatedAt": "2026-02-10T21:32:53.401Z"
}