{
  "summary": {
    "total": 30,
    "passed": 30,
    "failed": 0,
    "skipped": 0
  },
  "results": [
    {
      "testName": "button - Default",
      "status": "passed",
      "duration": 534.9000000000233
    },
    {
      "testName": "button - Disabled",
      "status": "passed",
      "duration": 379.5
    },
    {
      "testName": "button - Secondary",
      "status": "passed",
      "duration": 364.0999999999767
    },
    {
      "testName": "button - SecondaryDisabled",
      "status": "passed",
      "duration": 367.20000000001164
    },
    {
      "testName": "counter-button - Default",
      "status": "passed",
      "duration": 382.79999999998836
    },
    {
      "testName": "dialog - Default",
      "status": "passed",
      "duration": 368.1000000000349
    },
    {
      "testName": "components-drawer - Default",
      "status": "passed",
      "duration": 363.3999999999651
    },
    {
      "testName": "glass-screen - Default",
      "status": "passed",
      "duration": 367.5
    },
    {
      "testName": "icon-button - Active",
      "status": "passed",
      "duration": 366.5
    },
    {
      "testName": "icon-button - Default",
      "status": "passed",
      "duration": 365.20000000001164
    },
    {
      "testName": "icon-button - Disabled",
      "status": "passed",
      "duration": 366.3999999999651
    },
    {
      "testName": "motion-link - Default",
      "status": "passed",
      "duration": 366.5
    },
    {
      "testName": "number-input - Disabled",
      "status": "passed",
      "duration": 384.5999999999767
    },
    {
      "testName": "number-input - Primary",
      "status": "passed",
      "duration": 384.5
    },
    {
      "testName": "number-input - Secondary",
      "status": "passed",
      "duration": 382.69999999995343
    },
    {
      "testName": "number-input - WithLabel",
      "status": "passed",
      "duration": 382.0999999999767
    },
    {
      "testName": "number-input - WithMinMax",
      "status": "passed",
      "duration": 383.5
    },
    {
      "testName": "number-input - WithStep",
      "status": "passed",
      "duration": 382.79999999998836
    },
    {
      "testName": "popover - Default",
      "status": "passed",
      "duration": 365.29999999998836
    },
    {
      "testName": "radio - Default",
      "status": "passed",
      "duration": 385.6000000000349
    },
    {
      "testName": "reorder - Default",
      "status": "passed",
      "duration": 403.5999999999767
    },
    {
      "testName": "select - Default",
      "status": "passed",
      "duration": 379.5
    },
    {
      "testName": "select - ManyOptions",
      "status": "passed",
      "duration": 366.70000000001164
    },
    {
      "testName": "select - WithDefaultValue",
      "status": "passed",
      "duration": 365.9000000000233
    },
    {
      "testName": "select - WithOnValueChange",
      "status": "passed",
      "duration": 367
    },
    {
      "testName": "select - WithoutLabel",
      "status": "passed",
      "duration": 366.5
    },
    {
      "testName": "text-area - Default",
      "status": "passed",
      "duration": 384.29999999998836
    },
    {
      "testName": "text-input - Default",
      "status": "passed",
      "duration": 381.3999999999651
    },
    {
      "testName": "toast - Default",
      "status": "passed",
      "duration": 364.69999999995343
    },
    {
      "testName": "toast - LongMessage",
      "status": "passed",
      "duration": 366.3999999999651
    }
  ],
  "generatedAt": "2026-01-30T14:10:02.829Z"
}